calzone/__init__.py
calzone/metrics.py
calzone/utils.py
calzone/vis.py
calzone_tool-0.1.0.dist-info/LICENSE
calzone_tool-0.1.0.dist-info/METADATA
calzone_tool-0.1.0.dist-info/WHEEL
calzone_tool-0.1.0.dist-info/entry_points.txt
calzone_tool-0.1.0.dist-info/top_level.txt
calzone_tool-0.1.0.dist-info/RECORD
