Metadata-Version: 2.1
Name: calzone-tool
Version: 0.1.0
Summary: A package for calibration measurement and analysis
Author-email: "Kwok Lung (Jason) Fan" <Kwoklung.Fan@fda.hhs.gov>, Qian Cao <Qian.Cao@fda.hhs.gov>
License: MIT
Project-URL: Homepage, https://calzone-docs.readthedocs.io/en/latest/index.html
Project-URL: Issues, https://github.com/DIDSR/calzone/issues
Classifier: Development Status :: 3 - Alpha
Classifier: Programming Language :: Python :: 3
Classifier: License :: OSI Approved :: MIT License
Classifier: Operating System :: OS Independent
Requires-Python: >=3.7
License-File: LICENSE
Requires-Dist: numpy
Requires-Dist: scipy
Requires-Dist: matplotlib
Requires-Dist: statsmodels
